jax_zero_contour/__init__.py
jax_zero_contour/zero_contour_finder.py
jax_zero_contour/tests/__init__.py
jax_zero_contour/tests/test_contour_finder.py
jax_zero_contour-2.0.0.dist-info/licenses/LICENSE
jax_zero_contour-2.0.0.dist-info/WHEEL
jax_zero_contour-2.0.0.dist-info/METADATA
jax_zero_contour-2.0.0.dist-info/RECORD
